imwatermark/__init__.py
imwatermark/dwtDctSvd.py
imwatermark/maxDct.py
imwatermark/rivaGan.py
imwatermark/rivagan_decoder.onnx
imwatermark/rivagan_encoder.onnx
imwatermark/watermark.py
invisible_watermark-0.1.5.data/scripts/invisible-watermark
invisible_watermark-0.1.5.dist-info/LICENSE
invisible_watermark-0.1.5.dist-info/METADATA
invisible_watermark-0.1.5.dist-info/WHEEL
invisible_watermark-0.1.5.dist-info/top_level.txt
invisible_watermark-0.1.5.dist-info/RECORD
