Metadata-Version: 2.1
Name: invisible-watermark
Version: 0.1.5
Summary: The library for creating and decoding invisible image watermarks
Home-page: https://github.com/ShieldMnt/invisible-watermark
Author: Qingquan Wang
Author-email: wangqq1103@gmail.com
License: UNKNOWN
Platform: UNKNOWN
Classifier: Programming Language :: Python :: 3
Classifier: License :: OSI Approved :: MIT License
Classifier: Operating System :: POSIX :: Linux
Requires-Python: >=3.6
Requires-Dist: opencv-python (>=4.1.0.25)
Requires-Dist: torch
Requires-Dist: onnx
Requires-Dist: onnxruntime
Requires-Dist: Pillow (>=6.0.0)
Requires-Dist: PyWavelets (>=1.1.1)
Requires-Dist: numpy (>=1.17.0)
